deep_net/__init__.py
deep_net/initializers.py
deep_net-0.1.1.dist-info/LICENSE
deep_net-0.1.1.dist-info/METADATA
deep_net-0.1.1.dist-info/WHEEL
deep_net-0.1.1.dist-info/top_level.txt
deep_net-0.1.1.dist-info/RECORD
